{"display_name": "personalfinance", "title": "Personal Finance", "id": "2qstm", "subcribers": 16034161, "created_utc": 1234147332.0, "description": "**Featured posts**\n\n* [Scam alert: Ignore any private messages or chat requests. Private communication is not safe on Reddit.](https://www.reddit.com/r/personalfinance/comments/div0yy/ignore_any_private_messages_anyone_offering/?utm_source=reddit&utm_medium=usertext&utm_name=personalfinance&utm_content=t5_2qstm)\n* [Tax Filing Software Megathread](https://www.reddit.com/r/personalfinance/comments/s63hyl/tax_filing_software_megathread_a_comprehensive/)\n* [Coronavirus Megathread Update](https://www.reddit.com/r/personalfinance/comments/m2xirz/coronavirus_megathread_update_american_rescue/)\n\n**Explore our wiki**\n\n* [PRIME DIRECTIVE: How to handle $](https://www.reddit.com/r/personalfinance/wiki/commontopics)\n* [PF WIKI: Many questions answered](https://www.reddit.com/r/personalfinance/wiki/)\n* [15 to 20?](https://www.reddit.com/r/personalfinance/wiki/teachme)\n* [18 to 25?](https://www.reddit.com/r/personalfinance/wiki/young_adult)\n* [25 to 35?](https://www.reddit.com/r/personalfinance/wiki/early_career)\n* [35 to 45?](https://www.reddit.com/r/personalfinance/wiki/mid_career)\n* [Books and videos](https://www.reddit.com/r/personalfinance/wiki/readinglist)\n* [Credit](https://www.reddit.com/r/personalfinance/wiki/index#wiki_credit)\n* [Debt](https://www.reddit.com/r/personalfinance/wiki/debt)\n* [Retirement](https://www.reddit.com/r/personalfinance/wiki/index#wiki_retirement_accounts)\n* [Investing](https://www.reddit.com/r/personalfinance/wiki/index#wiki_investing)\n* [Windfalls $$$](https://www.reddit.com/r/personalfinance/wiki/windfall)\n* [PF RULES: Please read and follow](https://www.reddit.com/r/personalfinance/about/rules)\n\n---\n**Our mission and standards**\n\nGet your financial house in order, learn how to better manage your money, and invest for your future.\n\n[Here, please treat others with respect, stay on-topic, and avoid self-promotion.](https://www.reddit.com/r/personalfinance/about/rules)\n\n---\n**Filter by flair**\n\n* [Auto](https://www.reddit.com/r/personalfinance/search?restrict_sr=on&q=flair:Auto&feature=legacy_search#res-hide-options)\n* [Investing](https://www.reddit.com/r/personalfinance/search?restrict_sr=on&q=flair:Investing&feature=legacy_search#res-hide-options)\n* [Budgeting](https://www.reddit.com/r/personalfinance/search?restrict_sr=on&q=flair:Budgeting&feature=legacy_search#res-hide-options)\n* [Planning](https://www.reddit.com/r/personalfinance/search?restrict_sr=on&q=flair:Planning&feature=legacy_search#res-hide-options)\n* [Credit](https://www.reddit.com/r/personalfinance/search?restrict_sr=on&q=flair:Credit&feature=legacy_search#res-hide-options)\n* [Retirement](https://www.reddit.com/r/personalfinance/search?restrict_sr=on&q=flair:Retirement&feature=legacy_search#res-hide-options)\n* [Debt](https://www.reddit.com/r/personalfinance/search?restrict_sr=on&q=flair:Debt&feature=legacy_search#res-hide-options)\n* [Saving](https://www.reddit.com/r/personalfinance/search?restrict_sr=on&q=flair:Saving&feature=legacy_search#res-hide-options)\n* [Employment](https://www.reddit.com/r/personalfinance/search?restrict_sr=on&q=flair:Employment&feature=legacy_search#res-hide-options)\n* [Taxes](https://www.reddit.com/r/personalfinance/search?restrict_sr=on&q=flair:Taxes&feature=legacy_search#res-hide-options)\n* [Housing](https://www.reddit.com/r/personalfinance/search?restrict_sr=on&q=flair:Housing&feature=legacy_search#res-hide-options)\n* [Other](https://www.reddit.com/r/personalfinance/search?restrict_sr=on&q=flair:Other&feature=legacy_search#res-hide-options)\n* [Insurance](https://www.reddit.com/r/personalfinance/search?restrict_sr=on&q=flair:Insurance&feature=legacy_search#res-hide-options)\n* [Meta](https://www.reddit.com/r/personalfinance/search?restrict_sr=on&q=flair:Meta&feature=legacy_search#res-hide-options)\n\n---\n[**Come chat with us on IRC!**](https://www.reddit.com/r/personalfinance/wiki/snoonet)\n\n---\n**Official threads**\n\n* [Weekday Help and Victory](https://www.reddit.com/r/personalfinance/search?q=title%3A%28%22Weekday+Help%22+OR+%22Moronic+Monday%22%29+author%3A%28AutoModerator+OR+IndexBot%29&restrict_sr=on&sort=new&t=week#res-hide-options)\n* [Weekend Discussion and Victory](https://www.reddit.com/r/personalfinance/search?q=title%3A%28%22Weekend+Discussion%22+OR+%22Triumphant+Thursday%22%29+author%3A%28AutoModerator+OR+IndexBot%29&restrict_sr=on&sort=new&t=week#res-hide-options)\n* [30-Day Challenges](https://www.reddit.com/r/personalfinance/search?q=title%3A%28%2230-day+Challenge%22%29+author%3A%28AutoModerator+OR+IndexBot%29&restrict_sr=on&sort=new&t=year#res-hide-options)\n* [PF Megathreads](https://www.reddit.com/r/personalfinance/search?q=title%3A%28megathread+OR+%22mega+thread%22%29+author%3A%28PersonalFinanceMods+OR+AutoModerator+OR+dequeued+OR+IShouldBeDoingSmthin+OR+Mrme487%29&restrict_sr=on&include_over_18=on&sort=new&t=all#res-hide-options)\n* [Meta Discussions](https://www.reddit.com/r/personalfinance/search?restrict_sr=on&sort=new&q=flair%3AMeta&feature=legacy_search#res-hide-options)\n\n---\n**Related subreddits**\n\n|||\n|-|-|\n|[AlmostHomeless](/r/AlmostHomeless)|[CreditCards](/r/CreditCards)|\n|[CareerGuidance](/r/CareerGuidance)|[Frugal](/r/frugal)|\n|[EatCheapAndHealthy](/r/EatCheapAndHealthy)|[Insurance](/r/insurance)|\n|[Entrepreneur](/r/entrepreneur)|[Investing](/r/investing)|\n|[FinancialIndependence](/r/FinancialIndependence)|[Jobs](/r/jobs)|\n|[MealPrepSunday](/r/MealPrepSunday)|[LegalAdvice](/r/LegalAdvice)|\n|[MilitaryFinance](/r/MilitaryFinance)|[PFjerk](/r/PFjerk)|\n|[Relationships](/r/relationships)|[PFtools](/r/PFtools)|\n|[StudentLoans](/r/StudentLoans)|[RealEstate](/r/RealEstate)|\n|[WhatCarShouldIBuy](/r/WhatCarShouldIBuy)|[Tax](/r/tax)|\n\n---\n\n**Regional subreddits**\n\n||\n|-|\n|[Country index](/r/personalfinance/wiki/country_index)|\n\n||||\n|-|-|-|\n|[Brazil](/r/investimentos)|[Australia](/r/AusFinance)|[Denmark](/r/dkfinance)|\n|[Finland](/r/omatalous)|[Canada](/r/PersonalFinanceCanada)|[European Union](/r/EUpersonalfinance)|\n|[France](/r/vosfinances)|[Malaysia](/r/MalaysianPF)|[Germany](/r/finanzen)|\n|[India](/r/IndiaInvestments)|[Portugal](/r/literaciafinanceira)|[New Zealand](/r/PersonalFinanceNZ)|\n|[Italy](/r/ItaliaPersonalFinance)|[Sweden](/r/privatekonomi)|[United Kingdom](/r/UKPersonalFinance)|\n\n[](#/RES_SR_Config/NightModeCompatible)\n\n---\n\n[Always do your own research before acting on any information or advice that you read on Reddit.](/r/personalfinance/wiki/disclaimer)", "rules": {"rules": [{"kind": "link", "description": "#Please treat others with respect, stay on-topic, and avoid self-promotion.\n\nPosts must be a personal finance question or discussion with a descriptive title.\n\nWe don't allow:\n\n* Polls, surveys, or questions that ask others to answer for themselves\n* Hypothetical or improbable posts\n* Success stories or thanks (use weekday/weekend thread)\n* Meta posts\n* IAmA/AMA requests or posts\n* News without a discussion, quote, or summary\n\n#[Additional Rules and Best Practices](/r/personalfinance/w/rules)", "short_name": "Submission guidelines", "violation_reason": "Submission guidelines", "created_utc": 1652979978, "priority": 0, "description_html": "<!-- SC_OFF --><div class=\"md\"><h1>Please treat others with respect, stay on-topic, and avoid self-promotion.</h1>\n\n<p>Posts must be a personal finance question or discussion with a descriptive title.</p>\n\n<p>We don&#39;t allow:</p>\n\n<ul>\n<li>Polls, surveys, or questions that ask others to answer for themselves</li>\n<li>Hypothetical or improbable posts</li>\n<li>Success stories or thanks (use weekday/weekend thread)</li>\n<li>Meta posts</li>\n<li>IAmA/AMA requests or posts</li>\n<li>News without a discussion, quote, or summary</li>\n</ul>\n\n<h1><a href=\"/r/personalfinance/w/rules\">Additional Rules and Best Practices</a></h1>\n</div><!-- SC_ON -->"}, {"kind": "all", "description": "We don't allow:\n\n* Promotion of web content, products, services, companies, or anything else owned by you (or anyone affiliated with you), even if not monetized\n* Accounts with promotional profiles or usernames\n* Offering referral, invite, or affiliate links/codes\n* Soliciting business/investors, market research, media requests, or recruiting\n* Repeatedly or prominently stating financial credentials\n* PM/DM requests or offers\n\nRequires pre-approval: open source tools, customer service replies", "short_name": "Self-promotional advertising or soliciting", "violation_reason": "Self-promotional advertising or soliciting", "created_utc": 1652979978, "priority": 1, "description_html": "<!-- SC_OFF --><div class=\"md\"><p>We don&#39;t allow:</p>\n\n<ul>\n<li>Promotion of web content, products, services, companies, or anything else owned by you (or anyone affiliated with you), even if not monetized</li>\n<li>Accounts with promotional profiles or usernames</li>\n<li>Offering referral, invite, or affiliate links/codes</li>\n<li>Soliciting business/investors, market research, media requests, or recruiting</li>\n<li>Repeatedly or prominently stating financial credentials</li>\n<li>PM/DM requests or offers</li>\n</ul>\n\n<p>Requires pre-approval: open source tools, customer service replies</p>\n</div><!-- SC_ON -->"}, {"kind": "all", "description": "We don't allow:\n\n* Circlejerking or karmawhoring\n* Posting purely for upvotes or humor\n* Insincerity or dishonesty\n* Trolling, brigading, loaded questions, loaded language, or provoking unproductive conversation\n* Memes and low-effort content\n* Clickbait titles\n* Excessive large, bold, or spaced-out text\n* Bots and bot summoning\n* In-character novelty accounts\n* Insubstantive or ephemeral posts\n* Requesting votes in any way\n* Excessive profanity\n* [Poor reddiquette](https://bit.ly/2vKxaO6)", "short_name": "Unhelpful or disrespectful", "violation_reason": "Unhelpful or disrespectful", "created_utc": 1652979978, "priority": 2, "description_html": "<!-- SC_OFF --><div class=\"md\"><p>We don&#39;t allow:</p>\n\n<ul>\n<li>Circlejerking or karmawhoring</li>\n<li>Posting purely for upvotes or humor</li>\n<li>Insincerity or dishonesty</li>\n<li>Trolling, brigading, loaded questions, loaded language, or provoking unproductive conversation</li>\n<li>Memes and low-effort content</li>\n<li>Clickbait titles</li>\n<li>Excessive large, bold, or spaced-out text</li>\n<li>Bots and bot summoning</li>\n<li>In-character novelty accounts</li>\n<li>Insubstantive or ephemeral posts</li>\n<li>Requesting votes in any way</li>\n<li>Excessive profanity</li>\n<li><a href=\"https://bit.ly/2vKxaO6\">Poor reddiquette</a></li>\n</ul>\n</div><!-- SC_ON -->"}, {"kind": "all", "description": "We don't allow asking for handouts or transactions.  That includes:\n\n* Asking (even indirectly) for gifts, loans, or donations for yourself or on behalf of any organization or person(s)\n* Any mention of a fundraising campaign even without a link\n* Requesting a job\n* Asking for loan cosigners\n* Soliciting for anyone to engage in any kind of transaction", "short_name": "Asking for handouts or transactions", "violation_reason": "Asking for handouts or transactions", "created_utc": 1652979978, "priority": 3, "description_html": "<!-- SC_OFF --><div class=\"md\"><p>We don&#39;t allow asking for handouts or transactions.  That includes:</p>\n\n<ul>\n<li>Asking (even indirectly) for gifts, loans, or donations for yourself or on behalf of any organization or person(s)</li>\n<li>Any mention of a fundraising campaign even without a link</li>\n<li>Requesting a job</li>\n<li>Asking for loan cosigners</li>\n<li>Soliciting for anyone to engage in any kind of transaction</li>\n</ul>\n</div><!-- SC_ON -->"}, {"kind": "all", "description": "We don't allow legal or business discussions. That includes:\n\n- Discussions that are predominantly legal issues\n- Discussions about starting, funding, or running a business, corporation, partnership, etc.\n- Content better suited for /r/legaladvice, /r/smallbusiness, /r/entrepreneur, or /r/business", "short_name": "Legal or business discussion", "violation_reason": "Legal or business discussion", "created_utc": 1652979978, "priority": 4, "description_html": "<!-- SC_OFF --><div class=\"md\"><p>We don&#39;t allow legal or business discussions. That includes:</p>\n\n<ul>\n<li>Discussions that are predominantly legal issues</li>\n<li>Discussions about starting, funding, or running a business, corporation, partnership, etc.</li>\n<li>Content better suited for <a href=\"/r/legaladvice\">/r/legaladvice</a>, <a href=\"/r/smallbusiness\">/r/smallbusiness</a>, <a href=\"/r/entrepreneur\">/r/entrepreneur</a>, or <a href=\"/r/business\">/r/business</a></li>\n</ul>\n</div><!-- SC_ON -->"}, {"kind": "all", "description": "We don't allow:\n\n- Moralizing issues\n- Petitions or calls-to-action\n- Political discussions\n- Political baiting\n- Soapboxing\n", "short_name": "Politicizing", "violation_reason": "Politicizing", "created_utc": 1652979978, "priority": 5, "description_html": "<!-- SC_OFF --><div class=\"md\"><p>We don&#39;t allow:</p>\n\n<ul>\n<li>Moralizing issues</li>\n<li>Petitions or calls-to-action</li>\n<li>Political discussions</li>\n<li>Political baiting</li>\n<li>Soapboxing</li>\n</ul>\n</div><!-- SC_ON -->"}, {"kind": "all", "description": "We don't allow:\n\n* Suggesting another user perform an activity that is illegal, unlawful, or fraudulent in most jurisdictions\n* Linking to illegal content or lawbreaking information\n* Asking for advice on any of the above", "short_name": "Lawbreaking information", "violation_reason": "Lawbreaking information", "created_utc": 1652979978, "priority": 6, "description_html": "<!-- SC_OFF --><div class=\"md\"><p>We don&#39;t allow:</p>\n\n<ul>\n<li>Suggesting another user perform an activity that is illegal, unlawful, or fraudulent in most jurisdictions</li>\n<li>Linking to illegal content or lawbreaking information</li>\n<li>Asking for advice on any of the above</li>\n</ul>\n</div><!-- SC_ON -->"}, {"kind": "all", "description": "We don't allow:\n\n* Personal attacks\n * Raw criticism without any constructive feedback\n * Name-calling, flaming, shaming, or otherwise harassing another poster (or person being helped)\n * Telling a user to harm themselves or others\n* Abusive language\n * Intentionally rude or very harsh language\n * [Hate speech](/r/personalfinance/wiki/rules#wiki_definitions)\n * Suggesting [sex work](/r/personalfinance/wiki/rules#wiki_definitions) (even indirectly)\n * Retaliating in response to an affront", "short_name": "Personal attack or abusive language", "violation_reason": "Personal attack or abusive language", "created_utc": 1652979978, "priority": 7, "description_html": "<!-- SC_OFF --><div class=\"md\"><p>We don&#39;t allow:</p>\n\n<ul>\n<li>Personal attacks\n\n<ul>\n<li>Raw criticism without any constructive feedback</li>\n<li>Name-calling, flaming, shaming, or otherwise harassing another poster (or person being helped)</li>\n<li>Telling a user to harm themselves or others</li>\n</ul></li>\n<li>Abusive language\n\n<ul>\n<li>Intentionally rude or very harsh language</li>\n<li><a href=\"/r/personalfinance/wiki/rules#wiki_definitions\">Hate speech</a></li>\n<li>Suggesting <a href=\"/r/personalfinance/wiki/rules#wiki_definitions\">sex work</a> (even indirectly)</li>\n<li>Retaliating in response to an affront</li>\n</ul></li>\n</ul>\n</div><!-- SC_ON -->"}, {"kind": "all", "description": "We don't allow relationship or personal advice discussions. That includes:\n\n* Content better suited for /r/relationships\n* Recommending a poster end their relationship or start a new relationship\n* Posts about suicide or violence\n* Posts asking for advice on how to convince someone else to change their behavior\n* Relationship drama not essential to a question or discussion\n* Family planning advice, especially unsolicited or flippant\n* Career path or school choice questions\n* Medical advice", "short_name": "Relationship or personal advice discussion", "violation_reason": "Relationship or personal advice discussion", "created_utc": 1652979978, "priority": 8, "description_html": "<!-- SC_OFF --><div class=\"md\"><p>We don&#39;t allow relationship or personal advice discussions. That includes:</p>\n\n<ul>\n<li>Content better suited for <a href=\"/r/relationships\">/r/relationships</a></li>\n<li>Recommending a poster end their relationship or start a new relationship</li>\n<li>Posts about suicide or violence</li>\n<li>Posts asking for advice on how to convince someone else to change their behavior</li>\n<li>Relationship drama not essential to a question or discussion</li>\n<li>Family planning advice, especially unsolicited or flippant</li>\n<li>Career path or school choice questions</li>\n<li>Medical advice</li>\n</ul>\n</div><!-- SC_ON -->"}, {"kind": "all", "description": "* Missing\uff0dDisappearing after posting a discussion or posting for another with inadequate information or involvement\n* Hyping\uff0dPushing speculative, volatile, illiquid, or meme investments, especially flippantly, tersely, or implying huge returns\n* Rabble rousing\uff0dWe're not your personal army\n* Doxing\uff0dPosting or seeking personal information, dox attempts or threats\n* Flooding\uff0dPosting excessively frequently\n* Duplicates\uff0dReposting news or information\n* Plagiarism\uff0dNot giving credit properly", "short_name": "Other bad behavior", "violation_reason": "Other bad behavior", "created_utc": 1652979978, "priority": 9, "description_html": "<!-- SC_OFF --><div class=\"md\"><ul>\n<li>Missing\uff0dDisappearing after posting a discussion or posting for another with inadequate information or involvement</li>\n<li>Hyping\uff0dPushing speculative, volatile, illiquid, or meme investments, especially flippantly, tersely, or implying huge returns</li>\n<li>Rabble rousing\uff0dWe&#39;re not your personal army</li>\n<li>Doxing\uff0dPosting or seeking personal information, dox attempts or threats</li>\n<li>Flooding\uff0dPosting excessively frequently</li>\n<li>Duplicates\uff0dReposting news or information</li>\n<li>Plagiarism\uff0dNot giving credit properly</li>\n</ul>\n</div><!-- SC_ON -->"}], "site_rules": ["Spam", "Personal and confidential information", "Threatening, harassing, or inciting violence"], "site_rules_flow": [{"reasonTextToShow": "This is spam", "reasonText": "This is spam"}, {"reasonTextToShow": "This is misinformation", "reasonText": "This is misinformation"}, {"nextStepHeader": "In what way?", "reasonTextToShow": "This is abusive or harassing", "nextStepReasons": [{"nextStepHeader": "Who is the harassment targeted at?", "reasonTextToShow": "It's targeted harassment", "nextStepReasons": [{"reasonTextToShow": "At me", "reasonText": "It's targeted harassment at me"}, {"reasonTextToShow": "At someone else", "reasonText": "It's targeted harassment at someone else"}], "reasonText": ""}, {"nextStepHeader": "Who is the threat directed at?", "reasonTextToShow": "It threatens violence or physical harm", "nextStepReasons": [{"reasonTextToShow": "At me", "reasonText": "It threatens violence or physical harm at me"}, {"reasonTextToShow": "At someone else", "reasonText": "It threatens violence or physical harm at someone else"}], "reasonText": ""}, {"reasonTextToShow": "It's rude, vulgar or offensive", "reasonText": "It's rude, vulgar or offensive"}, {"reasonTextToShow": "It's abusing the report button", "canWriteNotes": true, "isAbuseOfReportButton": true, "notesInputTitle": "Additional information (optional)", "reasonText": "It's abusing the report button"}], "reasonText": ""}, {"nextStepHeader": "What issue?", "reasonTextToShow": "Other issues", "nextStepReasons": [{"complaintButtonText": "File a complaint", "complaintUrl": "https://www.reddit.com/api/report_redirect?thing=%25%28thing%29s&reason_code=COPYRIGHT&feature=from_r2", "complaintPageTitle": "File a complaint?", "reasonText": "It infringes my copyright", "reasonTextToShow": "It infringes my copyright", "fileComplaint": true, "complaintPrompt": "If you think content on Reddit violates your intellectual property, please file a complaint at the link below:"}, {"complaintButtonText": "File a complaint", "complaintUrl": "https://www.reddit.com/api/report_redirect?thing=%25%28thing%29s&reason_code=TRADEMARK&feature=from_r2", "complaintPageTitle": "File a complaint?", "reasonText": "It infringes my trademark rights", "reasonTextToShow": "It infringes my trademark rights", "fileComplaint": true, "complaintPrompt": "If you think content on Reddit violates your intellectual property, please file a complaint at the link below:"}, {"reasonTextToShow": "It's personal and confidential information", "reasonText": "It's personal and confidential information"}, {"reasonTextToShow": "It's sexual or suggestive content involving minors", "reasonText": "It's sexual or suggestive content involving minors"}, {"nextStepHeader": "Do you appear in the image?", "reasonTextToShow": "It's involuntary pornography", "nextStepReasons": [{"reasonTextToShow": "I appear in the image", "reasonText": "It's involuntary pornography and i appear in it"}, {"reasonTextToShow": "I do not appear in the image", "reasonText": "It's involuntary pornography and i do not appear in it"}], "reasonText": ""}, {"reasonTextToShow": "It's a transaction for prohibited goods or services", "reasonText": "It's a transaction for prohibited goods or services"}, {"complaintButtonText": "File a complaint", "complaintUrl": "https://www.reddit.com/api/report_redirect?thing=%25%28thing%29s&reason_code=NETZDG&feature=from_r2", "complaintPageTitle": "File a complaint?", "reasonText": "Report this content under NetzDG", "reasonTextToShow": "Report this content under NetzDG", "fileComplaint": true, "complaintPrompt": "This reporting procedure is only available for people in Germany. If you are in Germany and would like to report this content under the German Netzwerkdurchsetzungsgesetz (NetzDG) law you may file a complaint by clicking the link below."}, {"usernamesInputTitle": "Username", "reasonTextToShow": "Someone is considering suicide or serious self-harm.", "canSpecifyUsernames": true, "reasonText": "Someone is considering suicide or serious self-harm.", "requestCrisisSupport": true, "oneUsername": true}], "reasonText": ""}]}}